{"fr":{"SDG_GOAL":"Objectif 17. Renforcer les moyens de mettre en \u0153uvre le Partenariat mondial pour le d\u00e9veloppement durable et le revitaliser","SDG_TARGET":"17.14 Renforcer la coh\u00e9rence des politiques de d\u00e9veloppement durable","SDG_INDICATOR":"17.14.1 Nombre de pays ayant mis en place des m\u00e9canismes pour renforcer la coh\u00e9rence des politiques de d\u00e9veloppement durable","STAT_CONC_DEF":"cat\u00e9gorie III","COVERAGE":"Cat\u00e9gorie III"},"indicator":"17.14.1","target_id":"17.14","sdg_goal":"17","reporting_status":"notstarted","data_non_statistical":true,"graph_type":"line","indicator_sort_order":"17-14-01","indicator_name":"global_indicators.17-14-1-title","graph_title":"global_indicators.17-14-1-title"}